WaniKaniTools/__init__.py
WaniKaniTools/api.py
WaniKaniTools/community.py
WaniKaniTools/credentials.py
WaniKaniTools/dir.py
WaniKaniTools/login.py
WaniKaniTools/utils.py
WaniKaniTools-0.3.0.dist-info/METADATA
WaniKaniTools-0.3.0.dist-info/RECORD
WaniKaniTools-0.3.0.dist-info/WHEEL
WaniKaniTools-0.3.0.dist-info/top_level.txt
