Metadata-Version: 2.1
Name: WaniKaniTools
Version: 0.3.0
Summary: Working with WaniKani API, login, and Community.
Home-page: https://github.com/patarapolw/WaniKaniTools
Author: Pacharapol Withayasakpunt
Author-email: patarapolw@gmail.com
License: MIT
Keywords: WaniKani
Platform: UNKNOWN
Classifier: Development Status :: 4 - Beta
Classifier: Environment :: Console
Classifier: Intended Audience :: Developers
Classifier: Intended Audience :: Education
Classifier: License :: OSI Approved :: MIT License
Classifier: Natural Language :: Japanese
Classifier: Programming Language :: Python :: 2.7
Classifier: Programming Language :: Python :: 3.4
Classifier: Programming Language :: Python :: 3.5
Classifier: Programming Language :: Python :: 3.6
Classifier: Topic :: Utilities
Requires-Python: >=2.7
Provides-Extra: tests
Provides-Extra: full
Requires-Dist: requests
Requires-Dist: bs4
Requires-Dist: selenium
Provides-Extra: full
Requires-Dist: requests-html; extra == 'full'
Provides-Extra: tests
Requires-Dist: pytest; extra == 'tests'
Requires-Dist: jaconv; extra == 'tests'
